{
  "common": "Spreading Dogbane",
  "sci": "Apocynum androsaemifolium",
  "family": "Apocynaceae",
  "type": "Herb",
  "life": "Hardy herbaceous perennial",
  "edible_parts": "Not eaten.",
  "other_uses": "Pollinator plant; strong stem fiber (cordage).",
  "prep": "A tough fiber plant — dried stems yield strong cordage; grown for ecology, not food.",
  "harvest": "Blooms summer.",
  "sun": "Full sun to part shade",
  "soil": "Dry, well-drained soils.",
  "risks": "TOXIC (cardiac glycosides) — not edible.",
  "buy": "Native-plant nurseries and native seed suppliers.",
  "native_states": [
    "ME",
    "NH",
    "VT",
    "MA",
    "RI",
    "CT",
    "NY",
    "NJ",
    "PA",
    "DE",
    "MD",
    "DC",
    "WV",
    "VA",
    "OH",
    "IN",
    "IL",
    "MI",
    "WI",
    "MN",
    "IA",
    "NC",
    "SC",
    "GA",
    "FL",
    "AL",
    "MS",
    "TN",
    "KY",
    "AR",
    "LA",
    "MO",
    "ND",
    "SD",
    "MT",
    "CO",
    "WA",
    "OR"
  ],
  "native_regions": [],
  "native_to_us": true,
  "invasive_states": [],
  "invasive_everywhere": false,
  "dec_priority": true,
  "nf": false,
  "pol": true,
  "scores": {
    "raw": [
      0,
      "N"
    ],
    "cooked": [
      0,
      "N"
    ],
    "life": [
      8,
      "E"
    ],
    "eco": [
      7,
      "E"
    ],
    "materials": [
      6,
      "E"
    ],
    "med": [
      2,
      "A"
    ]
  },
  "sources": [
    [
      "Wikipedia",
      "https://en.wikipedia.org/wiki/Apocynum_androsaemifolium"
    ],
    [
      "Plants For A Future",
      "https://pfaf.org/user/plant.aspx?latinname=Apocynum+androsaemifolium"
    ],
    [
      "USDA PLANTS",
      "https://plants.usda.gov/plant-profile/APAN2"
    ]
  ]
}