{
  "common": "Hairy Grama",
  "sci": "Bouteloua hirsuta",
  "family": "Poaceae",
  "type": "Grass",
  "life": "Hardy herbaceous perennial",
  "edible_parts": "Not eaten (forage grass).",
  "other_uses": "Fine short-grass of dry glades and prairies with fuzzy seed spikes.",
  "prep": "Grown for dry-site restoration and low-water plantings; good forage. Not a human food.",
  "harvest": "Seed heads summer.",
  "sun": "Full sun",
  "soil": "Dry, rocky, well-drained soils; glades.",
  "risks": "None significant (not a food).",
  "buy": "Native-plant nurseries and native seed suppliers.",
  "native_states": [
    "MO",
    "KS",
    "NE",
    "IA",
    "IL",
    "MN",
    "WI",
    "SD",
    "ND",
    "OK",
    "TX",
    "AR",
    "IN",
    "CO",
    "NM",
    "TX"
  ],
  "native_regions": [],
  "native_to_us": true,
  "invasive_states": [],
  "invasive_everywhere": false,
  "dec_priority": false,
  "nf": false,
  "pol": false,
  "scores": {
    "raw": [
      0,
      "N"
    ],
    "cooked": [
      0,
      "N"
    ],
    "life": [
      7,
      "E"
    ],
    "eco": [
      7,
      "E"
    ],
    "materials": [
      4,
      "E"
    ],
    "med": [
      1,
      "A"
    ]
  },
  "sources": [
    [
      "Grow Native! (Missouri Prairie Foundation)",
      "https://grownative.org/native-plant-database/"
    ],
    [
      "Wikipedia",
      "https://en.wikipedia.org/wiki/Bouteloua_hirsuta"
    ],
    [
      "Photo — Bouteloua hirsuta (Poaceae), grama peluda",
      "https://commons.wikimedia.org/wiki/File%3ABouteloua_hirsuta_%28Poaceae%29%2C_grama_peluda.jpg"
    ],
    [
      "USDA PLANTS",
      "https://plants.usda.gov/plant-profile/BOHI2"
    ]
  ]
}