{
  "common": "Giant Bur-reed",
  "sci": "Sparganium eurycarpum",
  "family": "Typhaceae",
  "type": "Herb",
  "life": "Hardy herbaceous perennial",
  "edible_parts": "Rhizomes/tubers (historic, minor — mostly wildlife food).",
  "other_uses": "Larger pond-edge relative; important waterfowl and muskrat food.",
  "prep": "Rootstocks were occasionally eaten historically, boiled like other aquatic tubers; today grown chiefly for wildlife.",
  "harvest": "Tubers fall.",
  "sun": "Full sun to part shade",
  "soil": "Shallow standing water; marsh and pond margins.",
  "risks": "None significant.",
  "buy": "Native-plant nurseries and native seed suppliers.",
  "native_states": [
    "ME",
    "NH",
    "VT",
    "MA",
    "RI",
    "CT",
    "NY",
    "NJ",
    "PA",
    "DE",
    "MD",
    "DC",
    "WV",
    "VA",
    "OH",
    "IN",
    "IL",
    "MI",
    "WI",
    "MN",
    "IA",
    "NC",
    "SC",
    "GA",
    "FL",
    "AL",
    "MS",
    "TN",
    "KY",
    "AR",
    "LA",
    "MO",
    "ND",
    "SD",
    "NE",
    "KS",
    "MT",
    "WY",
    "CO",
    "ID",
    "WA",
    "OR",
    "CA"
  ],
  "native_regions": [],
  "native_to_us": true,
  "invasive_states": [],
  "invasive_everywhere": false,
  "dec_priority": true,
  "nf": false,
  "pol": false,
  "scores": {
    "raw": [
      1,
      "A"
    ],
    "cooked": [
      3,
      "A"
    ],
    "life": [
      8,
      "E"
    ],
    "eco": [
      7,
      "E"
    ],
    "materials": [
      2,
      "A"
    ],
    "med": [
      0,
      "N"
    ]
  },
  "sources": [
    [
      "Wikipedia",
      "https://en.wikipedia.org/wiki/Sparganium_eurycarpum"
    ],
    [
      "Plants For A Future",
      "https://pfaf.org/user/plant.aspx?latinname=Sparganium+eurycarpum"
    ],
    [
      "Photo — Sparganiumeurycarpum",
      "https://commons.wikimedia.org/wiki/File%3ASparganiumeurycarpum.jpg"
    ],
    [
      "USDA PLANTS",
      "https://plants.usda.gov/plant-profile/SPEU"
    ]
  ]
}