{
  "common": "Northern Blueberry",
  "sci": "Vaccinium boreale",
  "family": "Ericaceae",
  "type": "Shrub",
  "life": "Hardy woody groundcover",
  "edible_parts": "Fruit (sweet, raw or cooked).",
  "other_uses": "Tiny alpine/boreal lowbush blueberry of summits and barrens.",
  "prep": "Eat the sweet blue berries fresh or cooked like other blueberries; a diminutive alpine groundcover.",
  "harvest": "Fruit summer.",
  "sun": "Full sun to part shade",
  "soil": "Dry to moist, acidic, rocky alpine soils.",
  "risks": "None significant.",
  "buy": "Native-plant nurseries and native seed suppliers.",
  "native_states": [
    "NY",
    "NH",
    "ME",
    "VT"
  ],
  "native_regions": [],
  "native_to_us": true,
  "invasive_states": [],
  "invasive_everywhere": false,
  "dec_priority": false,
  "nf": false,
  "pol": false,
  "scores": {
    "raw": [
      7,
      "E"
    ],
    "cooked": [
      7,
      "E"
    ],
    "life": [
      6,
      "E"
    ],
    "eco": [
      6,
      "E"
    ],
    "materials": [
      1,
      "A"
    ],
    "med": [
      1,
      "A"
    ]
  },
  "sources": [
    [
      "Wikipedia",
      "https://en.wikipedia.org/wiki/Vaccinium_boreale"
    ],
    [
      "Plants For A Future",
      "https://pfaf.org/user/plant.aspx?latinname=Vaccinium+boreale"
    ],
    [
      "USDA PLANTS",
      "https://plants.usda.gov/plant-profile/VABO"
    ]
  ]
}